Apache-License-2.0.txt
LICENSE
MANIFEST.in
OFL-License.txt
README.rst
requirements.txt
setup.cfg
setup.py
sphinx_ops_theme/__init__.py
sphinx_ops_theme/breadcrumbs.html
sphinx_ops_theme/footer.html
sphinx_ops_theme/layout.html
sphinx_ops_theme/layout_old.html
sphinx_ops_theme/search.html
sphinx_ops_theme/searchbox.html
sphinx_ops_theme/theme.conf
sphinx_ops_theme/versions.html
sphinx_ops_theme.egg-info/PKG-INFO
sphinx_ops_theme.egg-info/SOURCES.txt
sphinx_ops_theme.egg-info/dependency_links.txt
sphinx_ops_theme.egg-info/not-zip-safe
sphinx_ops_theme.egg-info/requires.txt
sphinx_ops_theme.egg-info/top_level.txt
sphinx_ops_theme/static/css/badge_only.css
sphinx_ops_theme/static/css/theme.css
sphinx_ops_theme/static/fonts/Inconsolata-Bold.ttf
sphinx_ops_theme/static/fonts/Inconsolata-Regular.ttf
sphinx_ops_theme/static/fonts/Lato-Bold.ttf
sphinx_ops_theme/static/fonts/Lato-Regular.ttf
sphinx_ops_theme/static/fonts/RobotoSlab-Bold.ttf
sphinx_ops_theme/static/fonts/RobotoSlab-Regular.ttf
sphinx_ops_theme/static/fonts/fontawesome-webfont.eot
sphinx_ops_theme/static/fonts/fontawesome-webfont.svg
sphinx_ops_theme/static/fonts/fontawesome-webfont.ttf
sphinx_ops_theme/static/fonts/fontawesome-webfont.woff
sphinx_ops_theme/static/js/modernizr.min.js
sphinx_ops_theme/static/js/theme.js